config/__init__.py
config/config.py
data/__init__.py
env/EnvMultipleStock_trade.py
env/EnvMultipleStock_train.py
env/EnvMultipleStock_validation.py
env/StockTradingRLEnv.py
env/__init__.py
model/__init__.py
model/models.py
model/models_new.py
model/models_new_3months.py
model/models_parameters.py
preprocessing/__init__.py
preprocessing/preprocessors.py
drl_model-0.1.dist-info/LICENSE
drl_model-0.1.dist-info/METADATA
drl_model-0.1.dist-info/WHEEL
drl_model-0.1.dist-info/top_level.txt
drl_model-0.1.dist-info/RECORD
