Metadata-Version: 2.1
Name: drl-model
Version: 0.1
Summary: DRL logic
Home-page: https://github.com/pypa/sampleproject
Author: author-drl
Author-email: author-drl@example.com
License: UNKNOWN
Platform: UNKNOWN
Classifier: Programming Language :: Python :: 3
Classifier: License :: OSI Approved :: MIT License
Classifier: Operating System :: OS Independent
Requires-Python: ==3.7
Requires-Dist: numpy (>=1.16.4)
Requires-Dist: pandas (>=1.0.3)
Requires-Dist: stockstats
Requires-Dist: scikit-learn (>=0.21.0)
Requires-Dist: gym (>=0.15.3)
Requires-Dist: stable-baselines[mpi]
Requires-Dist: coloredlogs
Requires-Dist: ray[all]
Requires-Dist: tensorflow-gpu (==1.14)
Requires-Dist: ax-platform (==0.1.14)
Requires-Dist: joblib (>=0.15.1)
Requires-Dist: matplotlib (>=3.2.1)
Requires-Dist: botorch
Requires-Dist: ta (>=0.5.25)
Requires-Dist: yfinance
Requires-Dist: quantstats
Requires-Dist: TA-Lib (>=0.4.19)
